matrix_multiply/__init__.py
matrix_multiply/core.py
matrix_multiply_lib-1.0.0.dist-info/licenses/LICENSE
tests/__init__.py
tests/test_matrix.py
matrix_multiply_lib-1.0.0.dist-info/METADATA
matrix_multiply_lib-1.0.0.dist-info/WHEEL
matrix_multiply_lib-1.0.0.dist-info/top_level.txt
matrix_multiply_lib-1.0.0.dist-info/RECORD
